{
  "logs": [
    {
      "message": "Do the fandango",
      "attention": false,
      "tech": "Tony Stark",
      "date": "2021-02-24T19:57:45.649Z",
      "id": 1
    },
    {
      "message": "Thunderbolt and lightening",
      "attention": true,
      "tech": "Swiss Tony",
      "date": "2021-02-24T19:58:25.534Z",
      "id": 2
    },
    {
      "message": "Ch-ch-changes, turn and face the crowd",
      "attention": true,
      "tech": "Tony Stark",
      "date": "2021-02-24T20:05:52.037Z",
      "id": 3
    }
  ],
  "techs": [
    {
      "id": 1,
      "firstname": "Swiss",
      "lastname": "Tony"
    },
    {
      "id": 2,
      "firstname": "Big",
      "lastname": "Tommy"
    },
    {
      "id": 3,
      "firstname": "Johnny",
      "lastname": "Bravo"
    },
    {
      "id": 4,
      "firstname": "Danger",
      "lastname": "Mouse"
    },
    {
      "firstname": "Antony",
      "lastname": "Stark",
      "id": 5
    }
  ]
}
